{
    "kind": "collectionType",
    "collectionName": "blocks",
    "info": {
        "singularName": "block",
        "pluralName": "blocks",
        "displayName": "Block",
        "description": ""
    },
    "options": {
        "draftAndPublish": true
    },
    "pluginOptions": {},
    "attributes": {
        "name": {
            "type": "string",
            "required": true,
            "unique": true
        },
        "type": {
            "type": "enumeration",
            "required": true,
            "enum": [
                "billboard",
                "headline",
                "image",
                "highlight",
                "richtext"
            ]
        },
        "highlight": {
            "type": "relation",
            "relation": "oneToOne",
            "target": "api::highlight.highlight"
        },
        "rich_texts": {
            "type": "relation",
            "relation": "oneToMany",
            "target": "api::rich-text.rich-text"
        },
        "media": {
            "type": "relation",
            "relation": "oneToMany",
            "target": "api::media.media"
        },
        "billboard": {
            "type": "relation",
            "relation": "oneToOne",
            "target": "api::billboard.billboard"
        }
    }
}
